wardoff/__init__.py
wardoff/__main__.py
wardoff/cli.py
wardoff/tokenizer.py
wardoff/url.py
wardoff/utils.py
wardoff/venv.py
wardoff/analyzers/module.py
wardoff/analyzers/syntax.py
wardoff/tests/sample.py
wardoff/tests/test_cli.py
wardoff/tests/test_tokenizer.py
wardoff/tests/test_venv.py
wardoff/tests/test_wardoff.py
wardoff/tests/utils.py
wardoff/tests/analyzers/test_syntax.py
wardoff-0.0.2.dev9.dist-info/AUTHORS
wardoff-0.0.2.dev9.dist-info/METADATA
wardoff-0.0.2.dev9.dist-info/WHEEL
wardoff-0.0.2.dev9.dist-info/entry_points.txt
wardoff-0.0.2.dev9.dist-info/pbr.json
wardoff-0.0.2.dev9.dist-info/top_level.txt
wardoff-0.0.2.dev9.dist-info/RECORD
