Metadata-Version: 2.1
Name: wardoff
Version: 0.0.2.dev9
Summary: Find deprecations in your requirements and underlying libraries
Home-page: https://github.com/4383/wardoff/
Author: Hervé Beraud
Author-email: herveberaud.pro@gmail.com
License: MIT
Platform: UNKNOWN
Classifier: Development Status :: 1 - Planning
Classifier: Intended Audience :: Information Technology
Classifier: License :: OSI Approved :: MIT License
Classifier: Operating System :: POSIX
Classifier: Programming Language :: Python
Classifier: Programming Language :: Python :: 3.8
Requires: pbr
Requires-Python: >=3.8
